{
  "status": "OPTIMAL",
  "solve_time": 0.007916000000000001,
  "objective_value": -7690.0,
  "train_schedules": {
    "12301_Howrah_Rajdhani": {
      "schedule": {
        "Station_C": {
          "arrival": "00:00",
          "departure": "06:00",
          "dwell_minutes": 0
        },
        "Station_A": {
          "arrival": "06:45",
          "departure": "07:45",
          "dwell_minutes": 60
        },
        "Station_J": {
          "arrival": "08:33",
          "departure": "09:31",
          "dwell_minutes": 58
        },
        "Lonavala_Hold_Point": {
          "arrival": "10:16",
          "departure": "10:27",
          "dwell_minutes": 11
        },
        "Junction_Z": {
          "arrival": "10:39",
          "departure": "10:51",
          "dwell_minutes": 12
        },
        "Station_B": {
          "arrival": "11:03",
          "departure": "00:00",
          "dwell_minutes": 0
        }
      },
      "delays": {
        "Station_C": {
          "weather": 0,
          "maintenance": 0,
          "congestion": 0,
          "operational": 0
        },
        "Station_A": {
          "weather": 0,
          "maintenance": 0,
          "congestion": 0,
          "operational": 0
        },
        "Station_J": {
          "weather": 0,
          "maintenance": 0,
          "congestion": 0,
          "operational": 0
        },
        "Lonavala_Hold_Point": {
          "weather": 0,
          "maintenance": 0,
          "congestion": 0,
          "operational": 0
        },
        "Junction_Z": {
          "weather": 0,
          "maintenance": 0,
          "congestion": 0,
          "operational": 0
        },
        "Station_B": {
          "weather": 0,
          "maintenance": 0,
          "congestion": 0,
          "operational": 0
        }
      },
      "total_delay": 0,
      "type": "superfast",
      "priority": 5.0
    },
    "22301_Shatabdi_Express": {
      "schedule": {
        "Station_C": {
          "arrival": "00:00",
          "departure": "06:17",
          "dwell_minutes": 0
        },
        "Station_A": {
          "arrival": "06:32",
          "departure": "06:34",
          "dwell_minutes": 2
        },
        "Station_J": {
          "arrival": "06:50",
          "departure": "07:00",
          "dwell_minutes": 10
        },
        "Lonavala_Hold_Point": {
          "arrival": "07:45",
          "departure": "07:53",
          "dwell_minutes": 8
        },
        "Junction_Z": {
          "arrival": "08:05",
          "departure": "11:25",
          "dwell_minutes": 0
        }
      },
      "delays": {
        "Station_C": {
          "weather": 0,
          "maintenance": 0,
          "congestion": 0,
          "operational": 0
        },
        "Station_A": {
          "weather": 0,
          "maintenance": 0,
          "congestion": 0,
          "operational": 0
        },
        "Station_J": {
          "weather": 0,
          "maintenance": 0,
          "congestion": 0,
          "operational": 0
        },
        "Lonavala_Hold_Point": {
          "weather": 0,
          "maintenance": 0,
          "congestion": 0,
          "operational": 0
        },
        "Junction_Z": {
          "weather": 0,
          "maintenance": 0,
          "congestion": 0,
          "operational": 0
        }
      },
      "total_delay": 0,
      "type": "superfast",
      "priority": 4.5
    },
    "11301_Udyan_Express": {
      "schedule": {
        "Station_C": {
          "arrival": "00:00",
          "departure": "08:00",
          "dwell_minutes": 0
        },
        "Station_A": {
          "arrival": "08:15",
          "departure": "09:00",
          "dwell_minutes": 45
        },
        "Station_J": {
          "arrival": "09:16",
          "departure": "10:16",
          "dwell_minutes": 60
        },
        "Lonavala_Hold_Point": {
          "arrival": "11:01",
          "departure": "11:13",
          "dwell_minutes": 12
        },
        "Junction_Z": {
          "arrival": "11:25",
          "departure": "11:38",
          "dwell_minutes": 13
        },
        "Station_B": {
          "arrival": "11:50",
          "departure": "11:51",
          "dwell_minutes": 1
        },
        "Junction_X": {
          "arrival": "11:59",
          "departure": "00:00",
          "dwell_minutes": 0
        }
      },
      "delays": {
        "Station_C": {
          "weather": 0,
          "maintenance": 0,
          "congestion": 0,
          "operational": 0
        },
        "Station_A": {
          "weather": 0,
          "maintenance": 0,
          "congestion": 0,
          "operational": 0
        },
        "Station_J": {
          "weather": 0,
          "maintenance": 0,
          "congestion": 0,
          "operational": 0
        },
        "Lonavala_Hold_Point": {
          "weather": 0,
          "maintenance": 0,
          "congestion": 0,
          "operational": 0
        },
        "Junction_Z": {
          "weather": 0,
          "maintenance": 0,
          "congestion": 0,
          "operational": 0
        },
        "Station_B": {
          "weather": 0,
          "maintenance": 0,
          "congestion": 0,
          "operational": 0
        },
        "Junction_X": {
          "weather": 0,
          "maintenance": 0,
          "congestion": 0,
          "operational": 0
        }
      },
      "total_delay": 0,
      "type": "express",
      "priority": 4.0
    },
    "17301_Mumbai_Mail": {
      "schedule": {
        "Station_B": {
          "arrival": "00:00",
          "departure": "08:00",
          "dwell_minutes": 0
        },
        "Junction_Z": {
          "arrival": "08:12",
          "departure": "08:23",
          "dwell_minutes": 11
        },
        "Lonavala_Hold_Point": {
          "arrival": "08:35",
          "departure": "08:46",
          "dwell_minutes": 11
        },
        "Station_J": {
          "arrival": "09:31",
          "departure": "09:42",
          "dwell_minutes": 11
        },
        "Station_A": {
          "arrival": "09:58",
          "departure": "10:04",
          "dwell_minutes": 6
        },
        "Station_C": {
          "arrival": "10:19",
          "departure": "00:00",
          "dwell_minutes": 0
        }
      },
      "delays": {
        "Station_B": {
          "weather": 0,
          "maintenance": 0,
          "congestion": 0,
          "operational": 0
        },
        "Junction_Z": {
          "weather": 0,
          "maintenance": 0,
          "congestion": 0,
          "operational": 0
        },
        "Lonavala_Hold_Point": {
          "weather": 0,
          "maintenance": 0,
          "congestion": 0,
          "operational": 0
        },
        "Station_J": {
          "weather": 0,
          "maintenance": 0,
          "congestion": 0,
          "operational": 0
        },
        "Station_A": {
          "weather": 0,
          "maintenance": 0,
          "congestion": 0,
          "operational": 0
        },
        "Station_C": {
          "weather": 0,
          "maintenance": 0,
          "congestion": 0,
          "operational": 0
        }
      },
      "total_delay": 0,
      "type": "mail_express",
      "priority": 3.5
    },
    "51301_Local_Passenger": {
      "schedule": {
        "Station_C": {
          "arrival": "00:00",
          "departure": "06:30",
          "dwell_minutes": 0
        },
        "Station_A": {
          "arrival": "06:45",
          "departure": "06:49",
          "dwell_minutes": 4
        },
        "Station_J": {
          "arrival": "07:32",
          "departure": "07:45",
          "dwell_minutes": 13
        },
        "Lonavala_Hold_Point": {
          "arrival": "08:30",
          "departure": "00:00",
          "dwell_minutes": 0
        }
      },
      "delays": {
        "Station_C": {
          "weather": 0,
          "maintenance": 0,
          "congestion": 0,
          "operational": 0
        },
        "Station_A": {
          "weather": 0,
          "maintenance": 0,
          "congestion": 0,
          "operational": 0
        },
        "Station_J": {
          "weather": 0,
          "maintenance": 0,
          "congestion": 0,
          "operational": 0
        },
        "Lonavala_Hold_Point": {
          "weather": 0,
          "maintenance": 0,
          "congestion": 0,
          "operational": 0
        }
      },
      "total_delay": 0,
      "type": "passenger",
      "priority": 2.0
    },
    "59301_Mixed_Passenger": {
      "schedule": {
        "Junction_Z": {
          "arrival": "00:00",
          "departure": "07:30",
          "dwell_minutes": 0
        },
        "Station_B": {
          "arrival": "07:42",
          "departure": "08:42",
          "dwell_minutes": 60
        },
        "Junction_X": {
          "arrival": "08:50",
          "departure": "09:26",
          "dwell_minutes": 36
        },
        "Station_G": {
          "arrival": "09:35",
          "departure": "00:00",
          "dwell_minutes": 0
        }
      },
      "delays": {
        "Junction_Z": {
          "weather": 0,
          "maintenance": 0,
          "congestion": 0,
          "operational": 0
        },
        "Station_B": {
          "weather": 0,
          "maintenance": 0,
          "congestion": 0,
          "operational": 0
        },
        "Junction_X": {
          "weather": 0,
          "maintenance": 0,
          "congestion": 0,
          "operational": 0
        },
        "Station_G": {
          "weather": 0,
          "maintenance": 0,
          "congestion": 0,
          "operational": 0
        }
      },
      "total_delay": 0,
      "type": "passenger",
      "priority": 1.8
    },
    "56301_Container_Freight": {
      "schedule": {
        "Karjat_Hold_Point": {
          "arrival": "00:00",
          "departure": "04:00",
          "dwell_minutes": 0
        },
        "Station_C": {
          "arrival": "04:20",
          "departure": "04:40",
          "dwell_minutes": 20
        },
        "Station_A": {
          "arrival": "04:55",
          "departure": "05:05",
          "dwell_minutes": 10
        },
        "Station_J": {
          "arrival": "05:21",
          "departure": "05:21",
          "dwell_minutes": 0
        }
      },
      "delays": {
        "Karjat_Hold_Point": {
          "weather": 0,
          "maintenance": 0,
          "congestion": 0,
          "operational": 0
        },
        "Station_C": {
          "weather": 0,
          "maintenance": 0,
          "congestion": 0,
          "operational": 0
        },
        "Station_A": {
          "weather": 0,
          "maintenance": 0,
          "congestion": 0,
          "operational": 0
        },
        "Station_J": {
          "weather": 0,
          "maintenance": 0,
          "congestion": 0,
          "operational": 0
        }
      },
      "total_delay": 0,
      "type": "freight",
      "priority": 1.5
    },
    "52301_Coal_Goods": {
      "schedule": {
        "Karjat_Hold_Point": {
          "arrival": "00:00",
          "departure": "03:26",
          "dwell_minutes": 0
        },
        "Station_C": {
          "arrival": "03:50",
          "departure": "04:50",
          "dwell_minutes": 60
        },
        "Station_A": {
          "arrival": "05:05",
          "departure": "10:00",
          "dwell_minutes": 0
        }
      },
      "delays": {
        "Karjat_Hold_Point": {
          "weather": 0,
          "maintenance": 0,
          "congestion": 0,
          "operational": 0
        },
        "Station_C": {
          "weather": 0,
          "maintenance": 0,
          "congestion": 0,
          "operational": 0
        },
        "Station_A": {
          "weather": 0,
          "maintenance": 0,
          "congestion": 0,
          "operational": 0
        }
      },
      "total_delay": 0,
      "type": "goods",
      "priority": 1.0
    }
  },
  "performance_metrics": {
    "total_system_delay_minutes": 0,
    "average_delay_per_train": 0.0,
    "punctuality_percentage": 100.0,
    "on_time_trains": 8,
    "total_trains": 8
  },
  "operational_insights": {
    "weather_impact": "Low",
    "maintenance_impact": "Low",
    "single_track_bottlenecks": 3,
    "premium_train_performance": "Good"
  },
  "recommendations": [
    "\ud83d\udea7 BOTTLENECK: 3 single track sections",
    "   \u2022 Priority: Double tracking of Lonavala-Junction_Z section",
    "   \u2022 Add additional crossing loops",
    "   \u2022 Implement automatic block signaling"
  ]
}